llm_api_benchmark_mcp_server/main.py
llm_api_benchmark_mcp_server/utils/__init__.py
llm_api_benchmark_mcp_server/utils/concurrency.py
llm_api_benchmark_mcp_server/utils/latency.py
llm_api_benchmark_mcp_server/utils/openai_client.py
llm_api_benchmark_mcp_server/utils/random_prompt.py
llm_api_benchmark_mcp_server/utils/statistics.py
llm_api_benchmark_mcp_server/utils/throughput.py
llm_api_benchmark_mcp_server/utils/ttft.py
llm_api_benchmark_mcp_server-0.1.4.dist-info/licenses/LICENSE
llm_api_benchmark_mcp_server-0.1.4.dist-info/METADATA
llm_api_benchmark_mcp_server-0.1.4.dist-info/WHEEL
llm_api_benchmark_mcp_server-0.1.4.dist-info/entry_points.txt
llm_api_benchmark_mcp_server-0.1.4.dist-info/top_level.txt
llm_api_benchmark_mcp_server-0.1.4.dist-info/RECORD
