Metadata-Version: 2.4
Name: llm-api-benchmark-mcp-server
Version: 0.1.4
Summary: Runs a throughput benchmark for LLM APIs, measuring generation throughput, prompt throughput, and Time To First Token (TTFT) under various concurrency levels.
Requires-Python: >=3.12
License-File: LICENSE
Requires-Dist: mcp[cli]>=1.9.3
Requires-Dist: numpy>=2.3.1
Requires-Dist: openai>=1.90.0
Requires-Dist: requests>=2.32.4
Dynamic: license-file
